Qualisys_Python_IO/__init__.py
Qualisys_Python_IO/qualisys_tools.py
qualisys_python_io-0.0.3.dist-info/METADATA
qualisys_python_io-0.0.3.dist-info/WHEEL
qualisys_python_io-0.0.3.dist-info/licenses/LICENSE
qualisys_python_io-0.0.3.dist-info/RECORD
