Metadata-Version: 2.3
Name: Qualisys_Python_IO
Version: 0.0.3
Summary: A python packege to get data from qualisys cameras
Project-URL: Homepage, https://github.com/thomazed/qualisys_python_IO
Project-URL: Issues, https://github.com/thomazed/qualisys_python_IO/issues
Author-email: Thomaz Eduardo Hinka <thomazeduhinka@gmail.com>
License-File: LICENSE
Classifier: License :: OSI Approved :: MIT License
Classifier: Operating System :: OS Independent
Classifier: Programming Language :: Python :: 3
Requires-Python: >=3.8
Requires-Dist: qtm-rt
Requires-Dist: setuptools
